LICENSE
README.md
setup.py
sic42/__init__.py
sic42/deathmatch_config.json
sic42/main.py
sic42/math_utils.py
sic42/sic.py
sic42/utils.py
sic42/visualization.py
sic42.egg-info/PKG-INFO
sic42.egg-info/SOURCES.txt
sic42.egg-info/dependency_links.txt
sic42.egg-info/requires.txt
sic42.egg-info/top_level.txt
sic42/competitors/.DS_Store
sic42/competitors/Eater.py
sic42/competitors/Reproducer.py
sic42/icons/.DS_Store
sic42/icons/agent.png
sic42/icons/foods.png
sic42/icons/obstacle.png